Metadata-Version: 1.0
Name: odin-dl
Version: 0.0.1b0
Summary: Visual Layer Object Detection
Home-page: UNKNOWN
Author: João Pedro Santana
Author-email: joaopedrosantana020@gmail.com
License: BSD 3-Clause
Platform: UNKNOWN
